image_marciano/__init__.py
image_marciano/processing/__init__.py
image_marciano/processing/combination.py
image_marciano/processing/transformation.py
image_marciano/utils/__init__.py
image_marciano/utils/io.py
image_marciano/utils/plot.py
image_processing_marciano-0.0.1.dist-info/METADATA
image_processing_marciano-0.0.1.dist-info/WHEEL
image_processing_marciano-0.0.1.dist-info/top_level.txt
image_processing_marciano-0.0.1.dist-info/RECORD
