Metadata-Version: 2.1
Name: image_processing_marciano
Version: 0.0.1
Summary: Teste de Versao
Home-page: 
Author: Maricano Silva
Author-email: marpinheirosilva@gmail.com
Requires-Python: >=3.8
Requires-Dist: matplotlib
Requires-Dist: numpy
Requires-Dist: scikit-image>=0.16.1
